streamlit_slb_gallery/__init__.py
streamlit_slb_gallery/example.py
streamlit_slb_gallery/frontend/build/asset-manifest.json
streamlit_slb_gallery/frontend/build/favicon.ico
streamlit_slb_gallery/frontend/build/index.html
streamlit_slb_gallery/frontend/build/logo192.png
streamlit_slb_gallery/frontend/build/logo512.png
streamlit_slb_gallery/frontend/build/manifest.json
streamlit_slb_gallery/frontend/build/no-image.png
streamlit_slb_gallery/frontend/build/static/css/main.3ce919c7.css
streamlit_slb_gallery/frontend/build/static/js/206.4d185342.chunk.js
streamlit_slb_gallery/frontend/build/static/js/main.7db76494.js
streamlit_slb_gallery/frontend/build/static/js/main.7db76494.js.LICENSE.txt
streamlit_slb_gallery/frontend/public/favicon.ico
streamlit_slb_gallery/frontend/public/index.html
streamlit_slb_gallery/frontend/public/logo192.png
streamlit_slb_gallery/frontend/public/logo512.png
streamlit_slb_gallery/frontend/public/manifest.json
streamlit_slb_gallery/frontend/public/no-image.png
streamlit_slb_gallery/models/__init__.py
streamlit_slb_gallery-1.2.8.dist-info/LICENSE
streamlit_slb_gallery-1.2.8.dist-info/METADATA
streamlit_slb_gallery-1.2.8.dist-info/WHEEL
streamlit_slb_gallery-1.2.8.dist-info/top_level.txt
streamlit_slb_gallery-1.2.8.dist-info/RECORD
